Metadata-Version: 1.0
Name: distprob
Version: 0.1
Summary: Gaussian and Binomial distributions
Home-page: UNKNOWN
Author: irishwy_2
Author-email: UNKNOWN
License: UNKNOWN
Platform: UNKNOWN
